synck/__init__.py
synck/__version__.py
synck/paths.py
synck/preferences.py
synck/py.typed
synck/system_info.py
synck/gui/__init__.py
synck/gui/__main__.py
synck/gui/gui_preferences.py
synck/gui/main.py
synck-0.0.1.dist-info/METADATA
synck-0.0.1.dist-info/WHEEL
synck-0.0.1.dist-info/licenses/LICENSE
synck-0.0.1.dist-info/RECORD
